{
  "cookbook_path" : "../recipes/cookbooks/",
  "node_000" :
  {
    "hostname" : "node_000",
    "box" : "ubuntu_trusty_vbox",
    "memory_size" : "1024",
    "product" : {
      "name": "mariadb",
      "version": "10.0",
      "cnf_template" : "server1.cnf",
      "cnf_template_path": "~/build-scripts/test-setup-scripts/cnf"
    }

  },

  "node_001" :
  {
    "hostname" : "node_001",
    "box" : "ubuntu_precise_vbox",
    "memory_size" : "1024",
    "product" : {
      "name": "mariadb",
      "version": "10.0",
      "cnf_template" : "server2.cnf",
      "cnf_template_path": "~/build-scripts/test-setup-scripts/cnf"
    }
  },

  "node_002" :
  {
    "hostname" : "node_002",
    "box" : "centos_6_vbox",
    "memory_size" : "1024",
    "product" : {
      "name": "mariadb",
      "version": "10.0",
      "cnf_template" : "server3.cnf",
      "cnf_template_path": "~/build-scripts/test-setup-scripts/cnf"
    }
  },

  "node_003" :
  {
    "hostname" : "node_003",
    "box" : "debian_wheezy_vbox",
    "memory_size" : "1024",
    "product" : {
      "name": "mariadb",
      "version": "10.0",
      "cnf_template" : "server4.cnf",
      "cnf_template_path": "~/build-scripts/test-setup-scripts/cnf"
    }
  },

  "galera_000" :
  {
    "hostname" : "galera_000",
    "box" : "debian_wheezy_vbox",
    "memory_size" : "1024",
    "product" : {
      "name": "galera",
      "version": "5.5",
      "cnf_template" : "galera_server1.cnf",
      "cnf_template_path": "~/build-scripts/test-setup-scripts/cnf"
    }
  },

  "galera_001" :
  {
    "hostname" : "galera_001",
    "box" : "ubuntu_trusty_vbox",
    "memory_size" : "1024",
    "product" : {
      "name": "galera",
      "version": "5.5",
      "cnf_template" : "galera_server2.cnf",
      "cnf_template_path": "~/build-scripts/test-setup-scripts/cnf"
    }
  },

  "galera_002" :
  {
    "hostname" : "galera_002",
    "box" : "ubuntu_trusty_vbox",
    "memory_size" : "1024",
    "product" : {
      "name": "galera",
      "version": "5.5",
      "cnf_template" : "galera_server3.cnf",
      "cnf_template_path": "~/build-scripts/test-setup-scripts/cnf"
    }
  },

  "galera_003" :
  {
    "hostname" : "galera_003",
    "box" : "centos_6_vbox",
    "memory_size" : "1024",
    "product" : {
      "name": "galera",
      "version": "5.5",
      "cnf_template" : "galera_server4.cnf",
      "cnf_template_path": "~/build-scripts/test-setup-scripts/cnf"
    }
  },

  "maxscale" :
  {
    "hostname" : "maxscale",
    "box" : "centos_6_vbox",
    "product" : {
      "name" : "maxscale"
    },
    "memory_size" : "1024"
  }
}
